<archimate:ArchimateDiagramModel
    xmlns:xsi="http://www.w3.org/2001/XMLSchema-instance"
    xmlns:archimate="http://www.archimatetool.com/archimate"
    name="Architectuurprincipes"
    id="id-34f0cbf082f6403ba2709a6cbe30b3a2">
  <children
      xsi:type="archimate:DiagramModelArchimateObject"
      id="id-0ef50847db9e4dfca329cc4bcfa3dc14"
      font="1|Lucida Grande|9.0|0|COCOA|1|LucidaGrande"
      textAlignment="1"
      textPosition="2"
      imagePath="images/_K7oroF7-Ee-HD-tdVb1lBg.png"
      imagePosition="9">
    <features
        name="iconVisible"
        value="1"/>
    <features
        name="imageSource"
        value="1"/>
    <bounds
        x="192"
        y="84"
        width="553"
        height="553"/>
    <children
        xsi:type="archimate:DiagramModelArchimateObject"
        id="id-d9855cf46d7240d0a3c6afb31393f715">
      <bounds
          x="552"
          y="481"
          width="120"
          height="55"/>
      <archimateElement
          xsi:type="archimate:Principle"
          href="Principle_EAID_1D4BC46E_45C0_43f7_A479_79EC3511F777.xml#EAID_1D4BC46E_45C0_43f7_A479_79EC3511F777"/>
    </children>
    <archimateElement
        xsi:type="archimate:Meaning"
        href="Meaning_id-17efa093da1c4573b1d059b1a601f53e.xml#id-17efa093da1c4573b1d059b1a601f53e"/>
  </children>
  <children
      xsi:type="archimate:DiagramModelArchimateObject"
      id="id-f8e639426597415c82b0c0da71a3c10f">
    <bounds
        x="408"
        y="24"
        width="120"
        height="55"/>
    <archimateElement
        xsi:type="archimate:Principle"
        href="Principle_EAID_3AAC98E2_AF5C_4f43_93B3_A383F2A827F8.xml#EAID_3AAC98E2_AF5C_4f43_93B3_A383F2A827F8"/>
  </children>
  <children
      xsi:type="archimate:DiagramModelArchimateObject"
      id="id-42591c7e204f46a9b9f9c752b06ab41e">
    <bounds
        x="708"
        y="168"
        width="120"
        height="55"/>
    <archimateElement
        xsi:type="archimate:Principle"
        href="Principle_EAID_9D5AF9CC_8436_417a_B5D3_48AEF39804A3.xml#EAID_9D5AF9CC_8436_417a_B5D3_48AEF39804A3"/>
  </children>
  <children
      xsi:type="archimate:DiagramModelArchimateObject"
      id="id-bc6aa9a41d8c4b1a90e441f97e116a61">
    <bounds
        x="756"
        y="324"
        width="120"
        height="55"/>
    <archimateElement
        xsi:type="archimate:Principle"
        href="Principle_EAID_B15EC175_7F30_4c10_B0B1_C4A611F7C07B.xml#EAID_B15EC175_7F30_4c10_B0B1_C4A611F7C07B"/>
  </children>
  <children
      xsi:type="archimate:DiagramModelArchimateObject"
      id="id-498de36e26d340c3b8b6cbd44d314e34">
    <bounds
        x="720"
        y="480"
        width="120"
        height="55"/>
    <archimateElement
        xsi:type="archimate:Principle"
        href="Principle_EAID_322A3361_ABED_45b4_97E9_6BB6371D0805.xml#EAID_322A3361_ABED_45b4_97E9_6BB6371D0805"/>
  </children>
  <children
      xsi:type="archimate:DiagramModelArchimateObject"
      id="id-696ae436d1d44f16add8bda2d608b639">
    <bounds
        x="625"
        y="612"
        width="120"
        height="55"/>
    <archimateElement
        xsi:type="archimate:Principle"
        href="Principle_EAID_1D4BC46E_45C0_43f7_A479_79EC3511F777.xml#EAID_1D4BC46E_45C0_43f7_A479_79EC3511F777"/>
  </children>
  <children
      xsi:type="archimate:DiagramModelArchimateObject"
      id="id-fbf7242d6db549ca9c9ffffa5abe7ac7">
    <bounds
        x="403"
        y="648"
        width="132"
        height="55"/>
    <archimateElement
        xsi:type="archimate:Principle"
        href="Principle_EAID_A3AF9CE3_E882_485f_A0FA_7D8139C72605.xml#EAID_A3AF9CE3_E882_485f_A0FA_7D8139C72605"/>
  </children>
  <children
      xsi:type="archimate:DiagramModelArchimateObject"
      id="id-936fcd14167f4220b231660d3f1654d6">
    <bounds
        x="108"
        y="168"
        width="120"
        height="55"/>
    <archimateElement
        xsi:type="archimate:Principle"
        href="Principle_EAID_19C2F0EB_C60F_416f_A7D7_E113A8A10C53.xml#EAID_19C2F0EB_C60F_416f_A7D7_E113A8A10C53"/>
  </children>
  <children
      xsi:type="archimate:DiagramModelArchimateObject"
      id="id-6d694b2338574436bc9469c84734e997">
    <bounds
        x="60"
        y="324"
        width="120"
        height="55"/>
    <archimateElement
        xsi:type="archimate:Principle"
        href="Principle_EAID_5B9CD2F1_41BC_4f5e_80B8_3BFA0CCD0756.xml#EAID_5B9CD2F1_41BC_4f5e_80B8_3BFA0CCD0756"/>
  </children>
  <children
      xsi:type="archimate:DiagramModelArchimateObject"
      id="id-f7c54c3669d14df19e918576b46ff60b">
    <bounds
        x="84"
        y="480"
        width="132"
        height="55"/>
    <archimateElement
        xsi:type="archimate:Principle"
        href="Principle_EAID_CCAB99F4_4CE8_46a1_A9CD_CEB139DC562E.xml#EAID_CCAB99F4_4CE8_46a1_A9CD_CEB139DC562E"/>
  </children>
  <children
      xsi:type="archimate:DiagramModelArchimateObject"
      id="id-10863bfb42f54831b76e18111c27f60b">
    <bounds
        x="204"
        y="60"
        width="120"
        height="55"/>
    <archimateElement
        xsi:type="archimate:Principle"
        href="Principle_EAID_EBE0A5C4_E038_405b_9A01_8E851BFA7C6D.xml#EAID_EBE0A5C4_E038_405b_9A01_8E851BFA7C6D"/>
  </children>
  <children
      xsi:type="archimate:DiagramModelArchimateObject"
      id="id-701f5ef8ffd94a9bb628a2eb746042f7">
    <bounds
        x="625"
        y="60"
        width="120"
        height="55"/>
    <archimateElement
        xsi:type="archimate:Principle"
        href="Principle_EAID_84E56A02_45D6_41ff_BB3B_987F98D32545.xml#EAID_84E56A02_45D6_41ff_BB3B_987F98D32545"/>
  </children>
  <children
      xsi:type="archimate:DiagramModelArchimateObject"
      id="id-67f9caff8a75434fb87e30a5c5a60791">
    <bounds
        x="192"
        y="612"
        width="120"
        height="55"/>
    <archimateElement
        xsi:type="archimate:Principle"
        href="Principle_EAID_41C5211F_6278_4793_80C7_D29222182222.xml#EAID_41C5211F_6278_4793_80C7_D29222182222"/>
  </children>
</archimate:ArchimateDiagramModel>
